setup.py
pynteractive/Network.py
pynteractive/SimpleWebSocketServer.py
pynteractive/__init__.py
pynteractive/chart.py
pynteractive/datastruct.py
pynteractive/globals.py
pynteractive/graph.py
pynteractive/graphd3.py
pynteractive/htmlcolors.py
pynteractive/map.py
pynteractive/newickParser.py
pynteractive/phylotree.py
pynteractive/tree.py
pynteractive/visNetwork.py
pynteractive/webfiles.py
pynteractive/webserver.py
pynteractive.egg-info/PKG-INFO
pynteractive.egg-info/SOURCES.txt
pynteractive.egg-info/dependency_links.txt
pynteractive.egg-info/top_level.txt
pynteractive/../webfiles/index.html
pynteractive/../webfiles/css/leftOptions.css
pynteractive/../webfiles/css/page.css
pynteractive/../webfiles/css/page.css~
pynteractive/../webfiles/js/FileSaver.js
pynteractive/../webfiles/js/UIC.js
pynteractive/../webfiles/js/UIL.js
pynteractive/../webfiles/js/chartD3Element.js
pynteractive/../webfiles/js/chartElement.js
pynteractive/../webfiles/js/element.js
pynteractive/../webfiles/js/encodings.js
pynteractive/../webfiles/js/graphD3Element.js
pynteractive/../webfiles/js/graphElement.js
pynteractive/../webfiles/js/mapElement.js
pynteractive/../webfiles/js/phyloElement.js
pynteractive/../webfiles/js/treeD3Element.js
pynteractive/../webfiles/js/treeElement.js
pynteractive/../webfiles/js/wscom.js
pynteractive/../webfiles/libs/d3.min.js
pynteractive/../webfiles/libs/dndTree.js
pynteractive/../webfiles/libs/jquery-2.1.0.js
pynteractive/../webfiles/libs/jquery-2.1.0.min.js
pynteractive/../webfiles/libs/jquery-ui.css
pynteractive/../webfiles/libs/jquery-ui.js
pynteractive/../webfiles/libs/l.control.geosearch.js
pynteractive/../webfiles/libs/l.geosearch.css
pynteractive/../webfiles/libs/l.geosearch.provider.openstreetmap.js
pynteractive/../webfiles/libs/leaflet.css
pynteractive/../webfiles/libs/leaflet.js
pynteractive/../webfiles/libs/life.css
pynteractive/../webfiles/libs/nv.d3.css
pynteractive/../webfiles/libs/nv.d3.js
pynteractive/../webfiles/libs/packages.js
pynteractive/../webfiles/libs/style.css
pynteractive/../webfiles/libs/vis.css
pynteractive/../webfiles/libs/vis.js
pynteractive/../webfiles/libs/images/ajax-loader.gif
