Metadata-Version: 1.1
Name: pynteractive
Version: 1.1.0
Summary: Pynteractive, a suite to generate interactive Javascript graphics
Home-page: http://github.com/coelias/Pynteractive
Author: Carlos del Ojo Elias, Oriol Mazariegos Canellas
Author-email: deepbit@gmail.com, mazeitor@gmail.com
License: GPLv3
Keywords: plotting interactive graphics JS
Platform: UNKNOWN
Classifier: Development Status :: 3 - Alpha
Classifier: Intended Audience :: Science/Research
Classifier: Topic :: Scientific/Engineering :: Visualization
Classifier: License :: OSI Approved :: GNU General Public License v3 or later (GPLv3+)
Classifier: Programming Language :: Python :: 2
Classifier: Programming Language :: Python :: 2.6
Classifier: Programming Language :: Python :: 2.7
